tgear_sdk/__init__.py
tgear_sdk/models.py
tgear_sdk/data_management/Data_Collection.py
tgear_sdk/data_management/__init__.py
tgear_sdk/data_management/utilities/Data_Preprocessor.py
tgear_sdk/data_management/utilities/Info_Manager.py
tgear_sdk/hal/Tactigon_BLE.py
tgear_sdk/hal/Tactigon_Serial.py
tgear_sdk/hal/__init__.py
tgear_sdk/middleware/Tactigon_Gesture.cp38-win_amd64.pyd
tgear_sdk/middleware/Tactigon_Recorder.cp38-win_amd64.pyd
tgear_sdk/middleware/Tactigon_Speech.cp38-win_amd64.pyd
tgear_sdk/middleware/Tactigon_Speech_New.cp38-win_amd64.pyd
tgear_sdk/middleware/Tactigon_Tracking.cp38-win_amd64.pyd
tgear_sdk/middleware/__init__.cp38-win_amd64.pyd
tgear_sdk/middleware/utilities/Tactigon_RT_Computing.cp38-win_amd64.pyd
tgear_sdk/middleware/utilities/__init__.cp38-win_amd64.pyd
tgear_sdk/pi_client/Client.py
tgear_sdk/pi_client/utilities/Client_Account_Managment.py
tgear_sdk/utilities/Config_Manager.py
tgear_sdk/utilities/File_Operations.py
tgear_sdk/utilities/License_Manager.py
tgear_sdk/utilities/__init__.py
tgear_sdk-3.0.5.dist-info/LICENSE
tgear_sdk-3.0.5.dist-info/METADATA
tgear_sdk-3.0.5.dist-info/WHEEL
tgear_sdk-3.0.5.dist-info/top_level.txt
tgear_sdk-3.0.5.dist-info/RECORD
