Metadata-Version: 2.1
Name: tgear-sdk
Version: 3.0.5
Summary: Tactigon Gear SDK to connect to Tactigon Skin wereable platform
Author-email: "Next Industries s.r.l" <info@nextind.eu>
Project-URL: Homepage, https://nextind.eu
Classifier: Programming Language :: Python :: 3
Classifier: License :: OSI Approved :: MIT License
Classifier: Operating System :: OS Independent
Requires-Python: <3.9,>=3.8
License-File: LICENSE
Requires-Dist: scipy ==1.5.2
Requires-Dist: numpy ==1.17.3
Requires-Dist: bleak ==0.19.5
Requires-Dist: deepspeech-tflite ==0.9.3
Requires-Dist: scikit-learn ==0.23.1
Requires-Dist: webrtcvad ==2.0.10
Requires-Dist: PyAudio ==0.2.12
Requires-Dist: blue-st-sdk ==1.4.0
Requires-Dist: requests ==2.24.0
Requires-Dist: pandas ==1.1.2
